{"amendement": {"@xmlns": "http://schemas.assemblee-nationale.fr/referentiel", "uid": "AMANR5L17PO838901B1907P0D1N000955", "chronotag": "1762684575436", "legislature": "17", "identification": {"numeroLong": "955", "numeroOrdreDepot": "955", "prefixeOrganeExamen": "AN", "numeroRect": "0"}, "examenRef": "EXANR5L17PO838901B1907P0D1", "texteLegislatifRef": "PRJLANR5L17B1907", "triAmendement": "ksaaaaaaaaaaaaaaaaaaaaaaaaaaaaaaaaaaaaaaaaaaaaaaaab", "cardinaliteAmdtMultiples": "1", "amendementParentRef": {"@xmlns:xsi": "http://www.w3.org/2001/XMLSchema-instance", "@xsi:nil": "true"}, "signataires": {"auteur": {"typeAuteur": "D\u00e9put\u00e9", "gouvernementRef": {"@xmlns:xsi": "http://www.w3.org/2001/XMLSchema-instance", "@xsi:nil": "true"}, "acteurRef": "PA719286", "groupePolitiqueRef": "PO845485", "auteurRapporteurOrganeRef": {"@xmlns:xsi": "http://www.w3.org/2001/XMLSchema-instance", "@xsi:nil": "true"}}, "cosignataires": {"acteurRef": ["PA794554", "PA795244", "PA720976", "PA721110", "PA720960", "PA793796"]}, "suffixe": {"@xmlns:xsi": "http://www.w3.org/2001/XMLSchema-instance", "@xsi:nil": "true"}, "libelle": "M.&#160;Colombani,  M.&#160;Castiglione, M.&#160;Lenormand, M.&#160;Mathiasin, Mme&#160;Sanquer, M.&#160;Serva et M.&#160;Taupiac"}, "pointeurFragmentTexte": {"partieAmendableRef": {"@xmlns:xsi": "http://www.w3.org/2001/XMLSchema-instance", "@xsi:nil": "true"}, "division": {"titre": "Article 41", "articleDesignationCourte": "ART. 41", "articleDesignation": "ARTICLE 41", "type": "ARTICLE", "avant_A_Apres": "A", "divisionRattachee": {"@xmlns:xsi": "http://www.w3.org/2001/XMLSchema-instance", "@xsi:nil": "true"}, "articleAdditionnel": "false", "chapitreAdditionnel": "false", "urlDivisionTexteVise": "/17/textes/1907.asp#D_Article_41"}, "amendementStandard": {"alinea": {"@xmlns:xsi": "http://www.w3.org/2001/XMLSchema-instance", "@xsi:nil": "true"}}}, "corps": {"cartoucheInformatif": {"@xmlns:xsi": "http://www.w3.org/2001/XMLSchema-instance", "@xsi:nil": "true"}, "contenuAuteur": {"dispositif": "<p>Supprimer cet article.</p>", "avantAppel": {"@xmlns:xsi": "http://www.w3.org/2001/XMLSchema-instance", "@xsi:nil": "true"}, "exposeSommaire": "<p>L&#x2019;article 41 pr&#x00E9;voit d&#x2019;allonger de deux &#x00E0; cinq ans le d&#x00E9;lai permettant aux caisses de s&#x00E9;curit&#x00E9; sociale de recouvrer les indus de prestations ou de revenus, et d&#x2019;&#x00E9;tendre cette dur&#x00E9;e dans le cadre des proc&#x00E9;dures civiles d&#x2019;ex&#x00E9;cution.</p><p>Une telle mesure alourdirait consid&#x00E9;rablement la charge pesant sur les assur&#x00E9;s sociaux et les professionnels de sant&#x00E9;, qui se verraient expos&#x00E9;s &#x00E0; des redressements ou r&#x00E9;cup&#x00E9;rations sur une p&#x00E9;riode beaucoup plus longue, alors m&#x00EA;me que les montants en cause sont souvent li&#x00E9;s &#x00E0; des erreurs administratives ou &#x00E0; des d&#x00E9;lais de traitement des caisses.</p><p>Cet allongement cr&#x00E9;erait une ins&#x00E9;curit&#x00E9; juridique et financi&#x00E8;re pour les assur&#x00E9;s comme pour les acteurs du syst&#x00E8;me de sant&#x00E9;, sans garantie d&#x2019;efficacit&#x00E9; accrue dans le recouvrement.</p><p>Le pr&#x00E9;sent amendement propose donc de supprimer cet article, afin de maintenir le droit existant, qui fixe un d&#x00E9;lai raisonnable et &#x00E9;quilibr&#x00E9; de deux ans.</p>", "annexeExposeSommaire": {"@xmlns:xsi": "http://www.w3.org/2001/XMLSchema-instance", "@xsi:nil": "true"}}}, "cycleDeVie": {"dateDepot": "2025-10-30", "datePublication": "2025-11-09", "soumisArticle40": "false", "etatDesTraitements": {"etat": {"code": "RT", "libelle": "Retir\u00e9"}, "sousEtat": {"code": "RT", "libelle": "Retir\u00e9 apr\u00e8s publication"}}, "dateSort": {"@xmlns:xsi": "http://www.w3.org/2001/XMLSchema-instance", "@xsi:nil": "true"}, "sort": {"@xmlns:xsi": "http://www.w3.org/2001/XMLSchema-instance", "@xsi:nil": "true"}}, "representations": {"representation": {"nom": "PDF", "typeMime": {"type": "application", "subType": "PDF"}, "statutRepresentation": {"verbatim": "true", "canonique": "true", "officielle": "true", "transcription": "false", "enregistrement": "false"}, "repSource": {"@xmlns:xsi": "http://www.w3.org/2001/XMLSchema-instance", "@xsi:nil": "true"}, "offset": {"@xmlns:xsi": "http://www.w3.org/2001/XMLSchema-instance", "@xsi:nil": "true"}, "contenu": {"documentURI": "/base/AMANR5L17PO838901B1907P0D1N000955?format=pdf"}, "dateDispoRepresentation": {"@xmlns:xsi": "http://www.w3.org/2001/XMLSchema-instance", "@xsi:nil": "true"}}}, "seanceDiscussionRef": {"@xmlns:xsi": "http://www.w3.org/2001/XMLSchema-instance", "@xsi:nil": "true"}, "article99": "false", "loiReference": {"@xmlns:xsi": "http://www.w3.org/2001/XMLSchema-instance", "@xsi:nil": "true"}, "discussionCommune": {"@xmlns:xsi": "http://www.w3.org/2001/XMLSchema-instance", "@xsi:nil": "true"}, "discussionIdentique": {"@xmlns:xsi": "http://www.w3.org/2001/XMLSchema-instance", "@xsi:nil": "true"}, "accordGouvernementDepotHorsDelai": "Sans objet"}}