{"amendement": {"@xmlns": "http://schemas.assemblee-nationale.fr/referentiel", "uid": "AMANR5L17PO838901B1907P0D1N002078", "chronotag": "1762698976680", "legislature": "17", "identification": {"numeroLong": "2078", "numeroOrdreDepot": "2078", "prefixeOrganeExamen": "AN", "numeroRect": "0"}, "examenRef": "EXANR5L17PO838901B1907P0D1", "texteLegislatifRef": "PRJLANR5L17B1907", "triAmendement": "ebiaaaaaaaaaaaaaaaaaaaaaaaaaaaaaaaaaaaaaaaaaaaaaaabao", "cardinaliteAmdtMultiples": "1", "amendementParentRef": {"@xmlns:xsi": "http://www.w3.org/2001/XMLSchema-instance", "@xsi:nil": "true"}, "signataires": {"auteur": {"typeAuteur": "D\u00e9put\u00e9", "gouvernementRef": {"@xmlns:xsi": "http://www.w3.org/2001/XMLSchema-instance", "@xsi:nil": "true"}, "acteurRef": "PA841431", "groupePolitiqueRef": "PO845470", "auteurRapporteurOrganeRef": {"@xmlns:xsi": "http://www.w3.org/2001/XMLSchema-instance", "@xsi:nil": "true"}}, "cosignataires": {"@xmlns:xsi": "http://www.w3.org/2001/XMLSchema-instance", "@xsi:nil": "true"}, "suffixe": {"@xmlns:xsi": "http://www.w3.org/2001/XMLSchema-instance", "@xsi:nil": "true"}, "libelle": "Mme&#160;Colin-Oesterl&#233;"}, "pointeurFragmentTexte": {"partieAmendableRef": {"@xmlns:xsi": "http://www.w3.org/2001/XMLSchema-instance", "@xsi:nil": "true"}, "division": {"titre": "Article 22", "articleDesignationCourte": "ART. 22", "articleDesignation": "ARTICLE 22", "type": "ARTICLE", "avant_A_Apres": "A", "divisionRattachee": {"@xmlns:xsi": "http://www.w3.org/2001/XMLSchema-instance", "@xsi:nil": "true"}, "articleAdditionnel": "false", "chapitreAdditionnel": "false", "urlDivisionTexteVise": "/17/textes/1907.asp#D_Article_22"}, "amendementStandard": {"alinea": {"avant_A_Apres": {"@xmlns:xsi": "http://www.w3.org/2001/XMLSchema-instance", "@xsi:nil": "true"}, "numero": "5", "alineaDesignation": "Alin\u00e9a 5"}}}, "corps": {"cartoucheInformatif": {"@xmlns:xsi": "http://www.w3.org/2001/XMLSchema-instance", "@xsi:nil": "true"}, "contenuAuteur": {"dispositif": "<p style=\"text-align: justify;\">Supprimer l&#x2019;alin&#x00E9;a&nbsp;5.</p>", "avantAppel": {"@xmlns:xsi": "http://www.w3.org/2001/XMLSchema-instance", "@xsi:nil": "true"}, "exposeSommaire": "<p>L&#x2019;article 22 du projet de loi pr&#x00E9;voit la suppression de dispositions int&#x00E9;gr&#x00E9;es depuis 2019 dans l&#x2019;article L. 162-22-18 du code de la s&#x00E9;curit&#x00E9; sociale. Cette suppression est cens&#x00E9;e correspondre &#x00E0; une mesure de simplification face &#x00E0; la trop grande complexit&#x00E9; des r&#x00E8;gles r&#x00E9;gissant le financement des &#x00E9;tablissements de sant&#x00E9;.</p><p>En r&#x00E9;alit&#x00E9;, cette &#x00E9;volution risque de remettre en cause la transparence initialement voulue par le l&#x00E9;gislateur dans la r&#x00E9;partition de la dotation populationnelle entre les r&#x00E9;gions. Or, ce m&#x00E9;canisme a pr&#x00E9;cis&#x00E9;ment pour objectif de r&#x00E9;duire les in&#x00E9;galit&#x00E9;s territoriales dans l&#x2019;allocation des ressources.</p><p>C&#x2019;est dans cet esprit que l&#x2019;avis des organisations nationales les plus repr&#x00E9;sentatives des &#x00E9;tablissements de sant&#x00E9; avait &#x00E9;t&#x00E9; pr&#x00E9;vu lors de la cr&#x00E9;ation de la dotation populationnelle en psychiatrie. Cette dotation constitue, pour la plupart des &#x00E9;tablissements autoris&#x00E9;s en psychiatrie, une part essentielle de leur financement par les r&#x00E9;gimes obligatoires d&#x2019;assurance maladie. Si son poids est moindre pour les &#x00E9;tablissements &#x00AB; ex-OQN &#x00BB;, elle demeure n&#x00E9;anmoins d&#x00E9;terminante.</p><p>La suppression propos&#x00E9;e dans le projet de loi affaiblirait la transparence du processus d&#x2019;allocation des moyens, laissant les f&#x00E9;d&#x00E9;rations hospitali&#x00E8;res dans une incertitude accrue, tant au niveau national que r&#x00E9;gional, quant aux crit&#x00E8;res et modalit&#x00E9;s de calcul des dotations.</p><p>Le pr&#x00E9;sent amendement vise donc &#x00E0; pr&#x00E9;server cette exigence de transparence, indispensable &#x00E0; une r&#x00E9;partition &#x00E9;quitable et lisible des ressources allou&#x00E9;es aux &#x00E9;tablissements de sant&#x00E9; autoris&#x00E9;s en psychiatrie.</p><p>Cet amendement a &#x00E9;t&#x00E9; travaill&#x00E9; avec la F&#x00E9;d&#x00E9;ration de l'hospitalisation priv&#x00E9;e (FHP).&nbsp;</p>", "annexeExposeSommaire": {"@xmlns:xsi": "http://www.w3.org/2001/XMLSchema-instance", "@xsi:nil": "true"}}}, "cycleDeVie": {"dateDepot": "2025-10-31", "datePublication": "2025-11-08", "soumisArticle40": "true", "etatDesTraitements": {"etat": {"code": "DI", "libelle": "Discut\u00e9"}, "sousEtat": {"code": "DI", "libelle": "Non soutenu"}}, "dateSort": "2025-11-09T15:24:24+01:00", "sort": "Non soutenu"}, "representations": {"representation": {"nom": "PDF", "typeMime": {"type": "application", "subType": "PDF"}, "statutRepresentation": {"verbatim": "true", "canonique": "true", "officielle": "true", "transcription": "false", "enregistrement": "false"}, "repSource": {"@xmlns:xsi": "http://www.w3.org/2001/XMLSchema-instance", "@xsi:nil": "true"}, "offset": {"@xmlns:xsi": "http://www.w3.org/2001/XMLSchema-instance", "@xsi:nil": "true"}, "contenu": {"documentURI": "/base/AMANR5L17PO838901B1907P0D1N002078?format=pdf"}, "dateDispoRepresentation": {"@xmlns:xsi": "http://www.w3.org/2001/XMLSchema-instance", "@xsi:nil": "true"}}}, "seanceDiscussionRef": "RUANR5L17S2026IDS29958", "article99": "false", "loiReference": {"codeLoi": "0", "divisionCodeLoi": {"@xmlns:xsi": "http://www.w3.org/2001/XMLSchema-instance", "@xsi:nil": "true"}}, "discussionCommune": {"idDiscussion": "34253", "typePosition": "Dernier"}, "discussionIdentique": {"idDiscussion": "84111", "typePosition": "Dernier"}, "accordGouvernementDepotHorsDelai": "Sans objet"}}