{"amendement": {"@xmlns": "http://schemas.assemblee-nationale.fr/referentiel", "uid": "AMANR5L17PO59047B1906P2D1N000066", "chronotag": "1761740503198", "legislature": "17", "identification": {"numeroLong": "II-AE66", "numeroOrdreDepot": "66", "prefixeOrganeExamen": "CION_AFETR", "numeroRect": "0"}, "examenRef": "EXANR5L17PO59047B1906P2D1", "texteLegislatifRef": "PRJLANR5L17B1906", "triAmendement": "aeaaaaaaaaaaaaaaaaaaaaaaaaaaaaaaaaaaaaaaaaaaaaaaaaac", "cardinaliteAmdtMultiples": "1", "amendementParentRef": {"@xmlns:xsi": "http://www.w3.org/2001/XMLSchema-instance", "@xsi:nil": "true"}, "signataires": {"auteur": {"typeAuteur": "D\u00e9put\u00e9", "gouvernementRef": {"@xmlns:xsi": "http://www.w3.org/2001/XMLSchema-instance", "@xsi:nil": "true"}, "acteurRef": "PA793182", "groupePolitiqueRef": "PO845401", "auteurRapporteurOrganeRef": {"@xmlns:xsi": "http://www.w3.org/2001/XMLSchema-instance", "@xsi:nil": "true"}}, "cosignataires": {"acteurRef": ["PA794734", "PA842001", "PA793134", "PA720468", "PA841613", "PA793146", "PA795900", "PA794030", "PA793290", "PA793314", "PA794582", "PA795966", "PA794442"]}, "suffixe": {"@xmlns:xsi": "http://www.w3.org/2001/XMLSchema-instance", "@xsi:nil": "true"}, "libelle": "M.&#160;Bovet,  M.&#160;Guiniot, M.&#160;Bigot, M.&#160;Buisson, M.&#160;Chenu, M.&#160;de&#160;Fleurian, M.&#160;Dragon, Mme&#160;Hamelet, M.&#160;Jolly, Mme&#160;Lelouis, Mme&#160;Alexandra&#160;Masson, M.&#160;Pfeffer, M.&#160;Rambaud et Mme&#160;Robert-Dehault"}, "pointeurFragmentTexte": {"partieAmendableRef": {"@xmlns:xsi": "http://www.w3.org/2001/XMLSchema-instance", "@xsi:nil": "true"}, "division": {"titre": "ETAT B", "articleDesignationCourte": "ART. 49", "articleDesignation": "ARTICLE 49", "type": "ANNEXE", "avant_A_Apres": "A", "divisionRattachee": "ARTICLE 49", "articleAdditionnel": "false", "chapitreAdditionnel": "false", "urlDivisionTexteVise": "/17/textes/1906C.asp#D_Etat_B"}, "missionVisee": {"codeEtat": "B", "codeMissionMinefi": "TA", "libelleMission": "\u00c9cologie, d\u00e9veloppement et mobilit\u00e9 durables", "missionRef": "3331"}}, "corps": {"cartoucheInformatif": {"@xmlns:xsi": "http://www.w3.org/2001/XMLSchema-instance", "@xsi:nil": "true"}, "contenuAuteur": {"dispositifAmdtCreditPLF": {"listeProgrammes": {"programme": [{"libelle": "Infrastructures et services de transports", "programmeRef": "578337", "autorisationEngagement": "0", "creditPaiement": "0", "action": "modification", "lignesCredits": {"@xmlns:xsi": "http://www.w3.org/2001/XMLSchema-instance", "@xsi:nil": "true"}}, {"libelle": "Affaires maritimes, p\u00eache et aquaculture", "programmeRef": "578339", "autorisationEngagement": "0", "creditPaiement": "0", "action": "modification", "lignesCredits": {"@xmlns:xsi": "http://www.w3.org/2001/XMLSchema-instance", "@xsi:nil": "true"}}, {"libelle": "Paysages, eau et biodiversit\u00e9", "programmeRef": "578341", "autorisationEngagement": "0", "creditPaiement": "0", "action": "modification", "lignesCredits": {"@xmlns:xsi": "http://www.w3.org/2001/XMLSchema-instance", "@xsi:nil": "true"}}, {"libelle": "Expertise, information g\u00e9ographique et m\u00e9t\u00e9orologie", "programmeRef": "578343", "autorisationEngagement": "0", "creditPaiement": "0", "action": "modification", "lignesCredits": {"@xmlns:xsi": "http://www.w3.org/2001/XMLSchema-instance", "@xsi:nil": "true"}}, {"libelle": "Pr\u00e9vention des risques", "programmeRef": "578345", "autorisationEngagement": "0", "creditPaiement": "0", "action": "modification", "lignesCredits": {"@xmlns:xsi": "http://www.w3.org/2001/XMLSchema-instance", "@xsi:nil": "true"}}, {"libelle": "\u00c9nergie, climat et apr\u00e8s-mines", "programmeRef": "578347", "autorisationEngagement": "0", "creditPaiement": "0", "action": "modification", "lignesCredits": {"@xmlns:xsi": "http://www.w3.org/2001/XMLSchema-instance", "@xsi:nil": "true"}}, {"libelle": "Service public de l'\u00e9nergie", "programmeRef": "578349", "autorisationEngagement": "0", "creditPaiement": "0", "action": "modification", "lignesCredits": {"@xmlns:xsi": "http://www.w3.org/2001/XMLSchema-instance", "@xsi:nil": "true"}}, {"libelle": "Conduite et pilotage des politiques de l'\u00e9cologie, du d\u00e9veloppement et de la mobilit\u00e9 durables", "programmeRef": "578351", "autorisationEngagement": "0", "creditPaiement": "0", "action": "modification", "lignesCredits": {"@xmlns:xsi": "http://www.w3.org/2001/XMLSchema-instance", "@xsi:nil": "true"}}, {"libelle": "Fonds d'acc\u00e9l\u00e9ration de la transition \u00e9cologique dans les territoires", "programmeRef": "578353", "autorisationEngagement": "0", "creditPaiement": "-200000000", "action": "modification", "lignesCredits": {"@xmlns:xsi": "http://www.w3.org/2001/XMLSchema-instance", "@xsi:nil": "true"}}, {"libelle": "S\u00fbret\u00e9 nucl\u00e9aire et radioprotection", "programmeRef": "578355", "autorisationEngagement": "0", "creditPaiement": "0", "action": "modification", "lignesCredits": {"@xmlns:xsi": "http://www.w3.org/2001/XMLSchema-instance", "@xsi:nil": "true"}}, {"libelle": "Ecologie \u2013 mise en extinction du plan de relance", "programmeRef": "578357", "autorisationEngagement": "0", "creditPaiement": "0", "action": "modification", "lignesCredits": {"@xmlns:xsi": "http://www.w3.org/2001/XMLSchema-instance", "@xsi:nil": "true"}}]}, "soldeAE": "0", "soldeCP": "-200000000", "cpEgalAe": "false"}, "avantAppel": {"@xmlns:xsi": "http://www.w3.org/2001/XMLSchema-instance", "@xsi:nil": "true"}, "exposeSommaire": "<p>Le pr&#x00E9;sent amendement vise &#x00E0; supprimer la hausse de 200 millions d&#x2019;euros que conna&#x00EE;t le Fonds d&#x2019;acc&#x00E9;l&#x00E9;ration de la transition &#x00E9;cologique dans les territoires dans le projet de loi de finances pour 2026.</p><p>Alors que l&#x2019;&#x00C9;tat fait face &#x00E0; de fortes contraintes financi&#x00E8;res, il appara&#x00EE;t n&#x00E9;cessaire de concentrer les moyens publics sur des politiques prioritaires et de limiter les augmentations de cr&#x00E9;dits que nous ne pouvons assumer.&nbsp;&nbsp;</p><p>Le PAP 2026 souligne lui-m&#x00EA;me que la dotation 2026 &#x00AB; rend n&#x00E9;cessaire une priorisation des mesures &#x00BB;, or de nombreux dispositifs (Fonds chaleur de l&#x2019;ADEME, programmes europ&#x00E9;ens FEDER et LIFE ou encore le Fonds vert)&nbsp;poursuivent des objectifs similaires, ce qui cr&#x00E9;e un risque de chevauchement et de dispersion des cr&#x00E9;dits.</p><p>Dans ces conditions, le niveau de financement atteint depuis 2025 appara&#x00EE;t suffisant au regard du rythme de d&#x00E9;ploiement des projets et des capacit&#x00E9;s d&#x2019;ex&#x00E9;cution des collectivit&#x00E9;s territoriales.</p>", "annexeExposeSommaire": {"@xmlns:xsi": "http://www.w3.org/2001/XMLSchema-instance", "@xsi:nil": "true"}}}, "cycleDeVie": {"dateDepot": "2025-10-25", "datePublication": "2025-10-28", "soumisArticle40": "false", "etatDesTraitements": {"etat": {"code": "DI", "libelle": "Discut\u00e9"}, "sousEtat": {"code": "DI", "libelle": "Rejet\u00e9"}}, "dateSort": "2025-10-29T13:21:25+01:00", "sort": "Rejet\u00e9"}, "representations": {"representation": {"nom": "PDF", "typeMime": {"type": "application", "subType": "PDF"}, "statutRepresentation": {"verbatim": "true", "canonique": "true", "officielle": "true", "transcription": "false", "enregistrement": "false"}, "repSource": {"@xmlns:xsi": "http://www.w3.org/2001/XMLSchema-instance", "@xsi:nil": "true"}, "offset": {"@xmlns:xsi": "http://www.w3.org/2001/XMLSchema-instance", "@xsi:nil": "true"}, "contenu": {"documentURI": "/base/AMANR5L17PO59047B1906P2D1N000066?format=pdf"}, "dateDispoRepresentation": {"@xmlns:xsi": "http://www.w3.org/2001/XMLSchema-instance", "@xsi:nil": "true"}}}, "seanceDiscussionRef": {"@xmlns:xsi": "http://www.w3.org/2001/XMLSchema-instance", "@xsi:nil": "true"}, "article99": "false", "loiReference": {"codeLoi": "1", "divisionCodeLoi": "Fonds vert"}, "discussionCommune": {"@xmlns:xsi": "http://www.w3.org/2001/XMLSchema-instance", "@xsi:nil": "true"}, "discussionIdentique": {"@xmlns:xsi": "http://www.w3.org/2001/XMLSchema-instance", "@xsi:nil": "true"}, "accordGouvernementDepotHorsDelai": "Sans objet"}}