{"amendement": {"@xmlns": "http://schemas.assemblee-nationale.fr/referentiel", "uid": "AMANR5L17PO59048B1906P2D1N000394", "chronotag": "1762557558088", "legislature": "17", "identification": {"numeroLong": "II-CF394", "numeroOrdreDepot": "394", "prefixeOrganeExamen": "CION_FIN", "numeroRect": "0"}, "examenRef": "EXANR5L17PO59048B1906P2D1", "texteLegislatifRef": "PRJLANR5L17B1906", "triAmendement": "fsaaaaaaaaaaaaaaaaaaaaaaaaaaaaaaaaaaaaaaaaaaaaaaaau", "cardinaliteAmdtMultiples": "1", "amendementParentRef": {"@xmlns:xsi": "http://www.w3.org/2001/XMLSchema-instance", "@xsi:nil": "true"}, "signataires": {"auteur": {"typeAuteur": "D\u00e9put\u00e9", "gouvernementRef": {"@xmlns:xsi": "http://www.w3.org/2001/XMLSchema-instance", "@xsi:nil": "true"}, "acteurRef": "PA267763", "groupePolitiqueRef": "PO845485", "auteurRapporteurOrganeRef": {"@xmlns:xsi": "http://www.w3.org/2001/XMLSchema-instance", "@xsi:nil": "true"}}, "cosignataires": {"acteurRef": ["PA607619", "PA942", "PA719138"]}, "suffixe": {"@xmlns:xsi": "http://www.w3.org/2001/XMLSchema-instance", "@xsi:nil": "true"}, "libelle": "M.&#160;Bataille,  M.&#160;Molac, M.&#160;de&#160;Courson et M.&#160;Castellani"}, "pointeurFragmentTexte": {"partieAmendableRef": {"@xmlns:xsi": "http://www.w3.org/2001/XMLSchema-instance", "@xsi:nil": "true"}, "division": {"titre": "ARTICLE 76", "articleDesignationCourte": "ART. 76", "articleDesignation": "ARTICLE 76", "type": "ARTICLE", "avant_A_Apres": "A", "divisionRattachee": {"@xmlns:xsi": "http://www.w3.org/2001/XMLSchema-instance", "@xsi:nil": "true"}, "articleAdditionnel": "false", "chapitreAdditionnel": "false", "urlDivisionTexteVise": "/17/textes/1906C.asp#D_ARTICLE_76"}, "missionVisee": {"codeEtat": "B", "codeMissionMinefi": "RC", "libelleMission": "Relations avec les collectivit\u00e9s territoriales", "missionRef": "3359"}, "amendementStandard": {"alinea": {"avant_A_Apres": {"@xmlns:xsi": "http://www.w3.org/2001/XMLSchema-instance", "@xsi:nil": "true"}, "numero": "35", "alineaDesignation": "Alin\u00e9a 35"}}}, "corps": {"cartoucheInformatif": "Retir\u00e9 avant publication.", "contenuAuteur": {"@xmlns:xsi": "http://www.w3.org/2001/XMLSchema-instance", "@xsi:nil": "true"}}, "cycleDeVie": {"dateDepot": "2025-10-29", "datePublication": "2025-11-04", "soumisArticle40": "false", "etatDesTraitements": {"etat": {"code": "RT", "libelle": "Retir\u00e9"}, "sousEtat": {"code": "RT", "libelle": "Retir\u00e9 avant publication"}}, "dateSort": {"@xmlns:xsi": "http://www.w3.org/2001/XMLSchema-instance", "@xsi:nil": "true"}, "sort": {"@xmlns:xsi": "http://www.w3.org/2001/XMLSchema-instance", "@xsi:nil": "true"}}, "representations": {"representation": {"nom": "PDF", "typeMime": {"type": "application", "subType": "PDF"}, "statutRepresentation": {"verbatim": "true", "canonique": "true", "officielle": "true", "transcription": "false", "enregistrement": "false"}, "repSource": {"@xmlns:xsi": "http://www.w3.org/2001/XMLSchema-instance", "@xsi:nil": "true"}, "offset": {"@xmlns:xsi": "http://www.w3.org/2001/XMLSchema-instance", "@xsi:nil": "true"}, "contenu": {"documentURI": "/base/AMANR5L17PO59048B1906P2D1N000394?format=pdf"}, "dateDispoRepresentation": {"@xmlns:xsi": "http://www.w3.org/2001/XMLSchema-instance", "@xsi:nil": "true"}}}, "seanceDiscussionRef": {"@xmlns:xsi": "http://www.w3.org/2001/XMLSchema-instance", "@xsi:nil": "true"}, "article99": "false", "loiReference": {"@xmlns:xsi": "http://www.w3.org/2001/XMLSchema-instance", "@xsi:nil": "true"}, "discussionCommune": {"@xmlns:xsi": "http://www.w3.org/2001/XMLSchema-instance", "@xsi:nil": "true"}, "discussionIdentique": {"@xmlns:xsi": "http://www.w3.org/2001/XMLSchema-instance", "@xsi:nil": "true"}, "accordGouvernementDepotHorsDelai": "Sans objet"}}