{"amendement": {"@xmlns": "http://schemas.assemblee-nationale.fr/referentiel", "uid": "AMANR5L17PO838901BTC1181P0D1N000009", "chronotag": "1743540777418", "legislature": "17", "identification": {"numeroLong": "9", "numeroOrdreDepot": "9", "prefixeOrganeExamen": "AN", "numeroRect": "0"}, "examenRef": "EXANR5L17PO838901BTC1181P0D1", "texteLegislatifRef": "PIONANR5L17BTC1181", "triAmendement": "biaaaaaaaaaaaaaaaaaaaaaaaaaaaaaaaaaaaaaaaaaaaaaaaam", "cardinaliteAmdtMultiples": "1", "amendementParentRef": {"@xmlns:xsi": "http://www.w3.org/2001/XMLSchema-instance", "@xsi:nil": "true"}, "signataires": {"auteur": {"typeAuteur": "D\u00e9put\u00e9", "gouvernementRef": {"@xmlns:xsi": "http://www.w3.org/2001/XMLSchema-instance", "@xsi:nil": "true"}, "acteurRef": "PA841893", "groupePolitiqueRef": "PO845419", "auteurRapporteurOrganeRef": {"@xmlns:xsi": "http://www.w3.org/2001/XMLSchema-instance", "@xsi:nil": "true"}}, "cosignataires": {"acteurRef": ["PA840171", "PA840665", "PA642764", "PA840903", "PA1008", "PA841381", "PA841665", "PA842263", "PA842211", "PA841463", "PA774960", "PA608264", "PA840673", "PA840793"]}, "suffixe": {"@xmlns:xsi": "http://www.w3.org/2001/XMLSchema-instance", "@xsi:nil": "true"}, "libelle": "Mme&#160;Thi&#233;bault-Martinez,  M.&#160;Emmanuel&#160;Gr&#233;goire, Mme&#160;Allemand, M.&#160;Aviragnet, M.&#160;Christophle, M.&#160;David, Mme&#160;Pantel, M.&#160;F&#233;gn&#233;, Mme&#160;Hadizadeh, Mme&#160;Bellay, Mme&#160;Mercier, Mme&#160;Santiago, Mme&#160;Capdevielle, Mme&#160;Rossi et M.&#160;Pena"}, "pointeurFragmentTexte": {"partieAmendableRef": {"@xmlns:xsi": "http://www.w3.org/2001/XMLSchema-instance", "@xsi:nil": "true"}, "division": {"titre": "Article PREMIER", "articleDesignationCourte": "ART. PREMIER", "articleDesignation": "ARTICLE PREMIER", "type": "ARTICLE", "avant_A_Apres": "A", "divisionRattachee": {"@xmlns:xsi": "http://www.w3.org/2001/XMLSchema-instance", "@xsi:nil": "true"}, "articleAdditionnel": "false", "chapitreAdditionnel": "false", "urlDivisionTexteVise": "/17/textes/1181.asp#D_Article_1er"}, "amendementStandard": {"alinea": {"avant_A_Apres": {"@xmlns:xsi": "http://www.w3.org/2001/XMLSchema-instance", "@xsi:nil": "true"}, "numero": "5", "alineaDesignation": "Alin\u00e9a 5"}}}, "corps": {"cartoucheInformatif": {"@xmlns:xsi": "http://www.w3.org/2001/XMLSchema-instance", "@xsi:nil": "true"}, "contenuAuteur": {"dispositif": "<p style=\"text-align: justify;\">I.&nbsp;&#x2013;&nbsp;&#x00C0; la fin de la premi&#x00E8;re phrase de l&#x2019;alin&#x00E9;a&nbsp;5, substituer aux mots&nbsp;:&nbsp;</p><p style=\"text-align: justify;\">&#x00AB;&nbsp;et r&#x00E9;vocable&nbsp;&#x00BB;,&nbsp;</p><p style=\"text-align: justify;\">les mots&nbsp;:</p><p style=\"text-align: justify;\">&#x00AB;&nbsp;, r&#x00E9;vocable et non monnay&#x00E9;.&nbsp;&#x00BB;</p><p style=\"text-align: justify;\">II.&nbsp;&#x2013;&nbsp;En cons&#x00E9;quence, supprimer les deux derni&#x00E8;res phrases de l&#x2019;alin&#x00E9;a&nbsp;5.&nbsp;</p>", "avantAppel": {"@xmlns:xsi": "http://www.w3.org/2001/XMLSchema-instance", "@xsi:nil": "true"}, "exposeSommaire": "<p>Cet amendement de repli vise &#x00E0; pr&#x00E9;ciser qu&#x2019;un acte sexuel ne peut &#x00EA;tre consid&#x00E9;r&#x00E9; comme consenti lorsqu&#x2019;il est obtenu en &#x00E9;change d&#x2019;une r&#x00E9;mun&#x00E9;ration, d&#x2019;un avantage ou d&#x2019;une promesse de r&#x00E9;mun&#x00E9;ration ou d&#x2019;avantage.</p><p>Dans les contextes prostitutionnel et pornographique, la contrainte &#x00E9;conomique ou mat&#x00E9;rielle place les personnes concern&#x00E9;es dans une situation o&#x00F9; elles n&#x2019;ont d&#x2019;autre choix que de se soumettre &#x00E0; des actes sexuels pour obtenir ces contreparties. D&#x00E8;s lors, leur consentement ne saurait &#x00EA;tre consid&#x00E9;r&#x00E9; comme libre et &#x00E9;clair&#x00E9;, mais doit au contraire &#x00EA;tre pr&#x00E9;sum&#x00E9; contraint d&#x00E8;s l&#x2019;origine.</p>", "annexeExposeSommaire": {"@xmlns:xsi": "http://www.w3.org/2001/XMLSchema-instance", "@xsi:nil": "true"}}}, "cycleDeVie": {"dateDepot": "2025-03-28", "datePublication": "2025-03-28", "soumisArticle40": "false", "etatDesTraitements": {"etat": {"code": "DI", "libelle": "Discut\u00e9"}, "sousEtat": {"code": "DI", "libelle": "Rejet\u00e9"}}, "dateSort": "2025-04-01T22:52:56+02:00", "sort": "Rejet\u00e9"}, "representations": {"representation": {"nom": "PDF", "typeMime": {"type": "application", "subType": "PDF"}, "statutRepresentation": {"verbatim": "true", "canonique": "true", "officielle": "true", "transcription": "false", "enregistrement": "false"}, "repSource": {"@xmlns:xsi": "http://www.w3.org/2001/XMLSchema-instance", "@xsi:nil": "true"}, "offset": {"@xmlns:xsi": "http://www.w3.org/2001/XMLSchema-instance", "@xsi:nil": "true"}, "contenu": {"documentURI": "/base/AMANR5L17PO838901BTC1181P0D1N000009?format=pdf"}, "dateDispoRepresentation": {"@xmlns:xsi": "http://www.w3.org/2001/XMLSchema-instance", "@xsi:nil": "true"}}}, "seanceDiscussionRef": "RUANR5L17S2025IDS29261", "article99": "false", "loiReference": {"codeLoi": "1", "divisionCodeLoi": {"@xmlns:xsi": "http://www.w3.org/2001/XMLSchema-instance", "@xsi:nil": "true"}}, "discussionCommune": {"@xmlns:xsi": "http://www.w3.org/2001/XMLSchema-instance", "@xsi:nil": "true"}, "discussionIdentique": {"@xmlns:xsi": "http://www.w3.org/2001/XMLSchema-instance", "@xsi:nil": "true"}, "accordGouvernementDepotHorsDelai": "Sans objet"}}