{"amendement": {"@xmlns": "http://schemas.assemblee-nationale.fr/referentiel", "uid": "AMANR5L17PO838901BTC1617P0D1N000122", "chronotag": "1757950625071", "legislature": "17", "identification": {"numeroLong": "122", "numeroOrdreDepot": "122", "prefixeOrganeExamen": "AN", "numeroRect": "0"}, "examenRef": "EXANR5L17PO838901BTC1617P0D1", "texteLegislatifRef": "PRJLANR5L17BTC1617", "triAmendement": "laaaaaaaaaaaaaaaaaaaaaaaaaaaaaaaaaaaaaaaaaaaaaaaaaai", "cardinaliteAmdtMultiples": "1", "amendementParentRef": {"@xmlns:xsi": "http://www.w3.org/2001/XMLSchema-instance", "@xsi:nil": "true"}, "signataires": {"auteur": {"typeAuteur": "D\u00e9put\u00e9", "gouvernementRef": {"@xmlns:xsi": "http://www.w3.org/2001/XMLSchema-instance", "@xsi:nil": "true"}, "acteurRef": "PA736201", "groupePolitiqueRef": "PO845439", "auteurRapporteurOrganeRef": {"@xmlns:xsi": "http://www.w3.org/2001/XMLSchema-instance", "@xsi:nil": "true"}}, "cosignataires": {"acteurRef": ["PA793452", "PA795010", "PA795636", "PA795076", "PA610968", "PA793780", "PA588884", "PA841701", "PA795362", "PA795454", "PA840997", "PA841885", "PA841507", "PA794008", "PA721210", "PA841351", "PA793980", "PA841419", "PA842013", "PA840947", "PA794022", "PA794146", "PA841223", "PA842045", "PA793708", "PA793664", "PA794154", "PA794778", "PA722142", "PA610002", "PA795808", "PA796018", "PA841713", "PA793948", "PA2940"]}, "suffixe": {"@xmlns:xsi": "http://www.w3.org/2001/XMLSchema-instance", "@xsi:nil": "true"}, "libelle": "Mme&#160;Taill&#233;-Polian,  M.&#160;Davi, Mme&#160;Garin, M.&#160;Lucas-Lundy, Mme&#160;Sandrine&#160;Rousseau, M.&#160;Amirshahi, Mme&#160;Arrighi, Mme&#160;Autain, Mme&#160;Balage&#160;El&#160;Mariky, Mme&#160;Belluco, M.&#160;Ben&#160;Cheikh, M.&#160;Biteau, M.&#160;Arnaud&#160;Bonnet, M.&#160;Nicolas&#160;Bonnet, Mme&#160;Chatelain, M.&#160;Corbi&#232;re, M.&#160;Duplessy, M.&#160;Fournier, M.&#160;Damien&#160;Girard, M.&#160;Gustave, Mme&#160;Catherine&#160;Hervieu, M.&#160;Iordanoff, Mme&#160;Laernoes, M.&#160;Lahais, Mme&#160;Ozenne, M.&#160;Peytavie, Mme&#160;Pochon, M.&#160;Raux, Mme&#160;Regol, M.&#160;Ruffin, Mme&#160;Sas, Mme&#160;Sebaihi, Mme&#160;Simonnet, M.&#160;Tavernier, M.&#160;Thierry et Mme&#160;Voynet"}, "pointeurFragmentTexte": {"partieAmendableRef": {"@xmlns:xsi": "http://www.w3.org/2001/XMLSchema-instance", "@xsi:nil": "true"}, "division": {"titre": "Article 10", "articleDesignationCourte": "APR\u00c8S ART. 10", "articleDesignation": "APR\u00c8S L'ARTICLE 10, ins\u00e9rer l'article suivant:", "type": "ARTICLE", "avant_A_Apres": "Apr\u00e8s", "divisionRattachee": {"@xmlns:xsi": "http://www.w3.org/2001/XMLSchema-instance", "@xsi:nil": "true"}, "articleAdditionnel": "true", "chapitreAdditionnel": "false", "urlDivisionTexteVise": "/17/textes/1617.asp#D_Article_10"}, "amendementStandard": {"alinea": {"@xmlns:xsi": "http://www.w3.org/2001/XMLSchema-instance", "@xsi:nil": "true"}}}, "corps": {"cartoucheInformatif": {"@xmlns:xsi": "http://www.w3.org/2001/XMLSchema-instance", "@xsi:nil": "true"}, "contenuAuteur": {"dispositif": "<p style=\"text-align: justify;\">Le Gouvernement remet chaque ann&#x00E9;e au Parlement au plus tard au&nbsp;1<sup>er</sup>&nbsp;septembre un rapport d&#x00E9;taill&#x00E9; sur le co&#x00FB;t et l&#x2019;impact de l&#x2019;exon&#x00E9;ration pr&#x00E9;vu &#x00E0; l&#x2019;article&nbsp;4 de la loi portant transposition des accords nationaux interprofessionnels en faveur de l&#x2019;emploi des salari&#x00E9;s exp&#x00E9;riment&#x00E9;s et relatif &#x00E0; l&#x2019;&#x00E9;volution du dialogue social. Ce rapport pr&#x00E9;cise notamment le nombre de contrats concern&#x00E9;s, la taille des entreprises ou groupe d&#x2019;entreprises employeurs, la r&#x00E9;partition g&#x00E9;ographique des cdi.</p>", "avantAppel": {"@xmlns:xsi": "http://www.w3.org/2001/XMLSchema-instance", "@xsi:nil": "true"}, "exposeSommaire": "<p>Le gouvernement ouvre une exon&#x00E9;ration sociale &#x00E0; l&#x2019;occasion de ce projet de loi, dans le cadre de son nouveau &#x00AB;&#x202F;CDI senior&#x202F;&#x00BB;. Le groupe &#x00C9;cologiste et social est favorable aux politiques publiques qui redonnent des perspectives d&#x2019;emploi, notamment pour les salari&#x00E9;s exp&#x00E9;riment&#x00E9;s.</p><p>N&#x00E9;anmoins, il ne peut s'instaurer ainsi une exon&#x00E9;ration de contributions sociales, alors m&#x00EA;me que la S&#x00E9;curit&#x00E9; sociale est fragilis&#x00E9;e, en grande partie du fait d&#x2019;une politique de l&#x2019;offre incapable de compenser les cadeaux fiscaux et sociaux consentis aux entreprises. Aucune &#x00E9;tude d&#x2019;impact budg&#x00E9;taire s&#x00E9;rieuse n&#x2019;est propos&#x00E9;e, aucun chiffrage clair n&#x2019;est transmis. Cela contrevient aux exigences de sinc&#x00E9;rit&#x00E9; et d&#x2019;&#x00E9;valuation pr&#x00E9;alable qui s&#x2019;imposent au gouvernement. Quelques mois &#x00E0; peine apr&#x00E8;s que la majorit&#x00E9; soutenant le pr&#x00E9;sident Emmanuel Macron a r&#x00E9;form&#x00E9; la LOLFSS et renforc&#x00E9; le suivi des exon&#x00E9;rations sociales, elle se place d&#x00E9;j&#x00E0; &#x00E0; la limite des r&#x00E8;gles qu&#x2019;elle a elle-m&#x00EA;me &#x00E9;dict&#x00E9;es.</p><p>C&#x2019;est pourquoi notre amendement vise &#x00E0; conditionner cette mesure &#x00E0; la production annuelle de donn&#x00E9;es robustes, accessibles et publiquement disponibles, afin que la repr&#x00E9;sentation nationale puisse exercer pleinement son r&#x00F4;le de contr&#x00F4;le.</p>", "annexeExposeSommaire": {"@xmlns:xsi": "http://www.w3.org/2001/XMLSchema-instance", "@xsi:nil": "true"}}}, "cycleDeVie": {"dateDepot": "2025-06-30", "datePublication": "2025-07-03", "soumisArticle40": "false", "etatDesTraitements": {"etat": {"code": "DI", "libelle": "Discut\u00e9"}, "sousEtat": {"code": "DI", "libelle": "Rejet\u00e9"}}, "dateSort": "2025-07-03T17:40:05+02:00", "sort": "Rejet\u00e9"}, "representations": {"representation": {"nom": "PDF", "typeMime": {"type": "application", "subType": "PDF"}, "statutRepresentation": {"verbatim": "true", "canonique": "true", "officielle": "true", "transcription": "false", "enregistrement": "false"}, "repSource": {"@xmlns:xsi": "http://www.w3.org/2001/XMLSchema-instance", "@xsi:nil": "true"}, "offset": {"@xmlns:xsi": "http://www.w3.org/2001/XMLSchema-instance", "@xsi:nil": "true"}, "contenu": {"documentURI": "/base/AMANR5L17PO838901BTC1617P0D1N000122?format=pdf"}, "dateDispoRepresentation": {"@xmlns:xsi": "http://www.w3.org/2001/XMLSchema-instance", "@xsi:nil": "true"}}}, "seanceDiscussionRef": "RUANR5L17S2025IDS29601", "article99": "false", "loiReference": {"codeLoi": "Z3", "divisionCodeLoi": {"@xmlns:xsi": "http://www.w3.org/2001/XMLSchema-instance", "@xsi:nil": "true"}}, "discussionCommune": {"@xmlns:xsi": "http://www.w3.org/2001/XMLSchema-instance", "@xsi:nil": "true"}, "discussionIdentique": {"@xmlns:xsi": "http://www.w3.org/2001/XMLSchema-instance", "@xsi:nil": "true"}, "accordGouvernementDepotHorsDelai": "Sans objet"}}