{"amendement": {"@xmlns": "http://schemas.assemblee-nationale.fr/referentiel", "uid": "AMANR5L17PO838901BTC1281P0D1N000794", "chronotag": "1757948074595", "legislature": "17", "identification": {"numeroLong": "794", "numeroOrdreDepot": "794", "prefixeOrganeExamen": "AN", "numeroRect": "0"}, "examenRef": "EXANR5L17PO838901BTC1281P0D1", "texteLegislatifRef": "PIONANR5L17BTC1281", "triAmendement": "gaaaaaaaaaaaaaaaaaaaaaaaaaaaaaaaaaaaaaaaaaaaaaaaaaebc", "cardinaliteAmdtMultiples": "1", "amendementParentRef": "AMANR5L17PO838901BTC1281P0D1N000263", "signataires": {"auteur": {"typeAuteur": "D\u00e9put\u00e9", "gouvernementRef": {"@xmlns:xsi": "http://www.w3.org/2001/XMLSchema-instance", "@xsi:nil": "true"}, "acteurRef": "PA841183", "groupePolitiqueRef": "PO847173", "auteurRapporteurOrganeRef": {"@xmlns:xsi": "http://www.w3.org/2001/XMLSchema-instance", "@xsi:nil": "true"}}, "cosignataires": {"@xmlns:xsi": "http://www.w3.org/2001/XMLSchema-instance", "@xsi:nil": "true"}, "suffixe": {"@xmlns:xsi": "http://www.w3.org/2001/XMLSchema-instance", "@xsi:nil": "true"}, "libelle": "Mme&#160;Mansouri"}, "pointeurFragmentTexte": {"partieAmendableRef": {"@xmlns:xsi": "http://www.w3.org/2001/XMLSchema-instance", "@xsi:nil": "true"}, "division": {"titre": "Article 11", "articleDesignationCourte": "ART. 11", "articleDesignation": "ARTICLE 11", "type": "ARTICLE", "avant_A_Apres": "A", "divisionRattachee": {"@xmlns:xsi": "http://www.w3.org/2001/XMLSchema-instance", "@xsi:nil": "true"}, "articleAdditionnel": "false", "chapitreAdditionnel": "false", "urlDivisionTexteVise": "/17/textes/1281.asp#D_Article_11"}, "amendementStandard": {"alinea": {"avant_A_Apres": {"@xmlns:xsi": "http://www.w3.org/2001/XMLSchema-instance", "@xsi:nil": "true"}, "numero": "3", "alineaDesignation": "Alin\u00e9a 3"}}}, "corps": {"cartoucheInformatif": {"@xmlns:xsi": "http://www.w3.org/2001/XMLSchema-instance", "@xsi:nil": "true"}, "contenuAuteur": {"dispositif": "<p style=\"text-align: justify;\">Compl&#x00E9;ter l&#x2019;alin&#x00E9;a&nbsp;4 par les mots&nbsp;:&nbsp;</p><p style=\"text-align: justify;\">&#x00AB;&nbsp;mentionn&#x00E9;s &#x00E0; l&#x2019;article&nbsp;L.&nbsp;1110&#x2011;10&nbsp;&#x00BB;.</p>", "avantAppel": {"@xmlns:xsi": "http://www.w3.org/2001/XMLSchema-instance", "@xsi:nil": "true"}, "exposeSommaire": "<p>Le pr&#x00E9;sent amendement vise &#x00E0; recentrer strictement l&#x2019;usage de la notion de soins &#x00E0; vis&#x00E9;e palliative sur la d&#x00E9;finition donn&#x00E9;e &#x00E0; l&#x2019;article L. 1110&#x2011;10 du code de la sant&#x00E9; publique, afin d&#x2019;en garantir la coh&#x00E9;rence et la port&#x00E9;e juridique.</p><p>En s&#x2019;appuyant explicitement sur la d&#x00E9;finition l&#x00E9;gale, le texte &#x00E9;vite les interpr&#x00E9;tations extensives et pr&#x00E9;serve la sp&#x00E9;cificit&#x00E9; des soins palliatifs, qui visent une prise en charge globale de la douleur et de la souffrance physique, psychique, sociale et spirituelle, sans vis&#x00E9;e curative.</p><p>Cette clarification est n&#x00E9;cessaire pour garantir la s&#x00E9;curit&#x00E9; juridique des dispositifs envisag&#x00E9;s et l&#x2019;orientation coh&#x00E9;rente des politiques publiques en mati&#x00E8;re de soins palliatifs.</p>", "annexeExposeSommaire": {"@xmlns:xsi": "http://www.w3.org/2001/XMLSchema-instance", "@xsi:nil": "true"}}}, "cycleDeVie": {"dateDepot": "2025-05-13", "datePublication": "2025-05-14", "soumisArticle40": "false", "etatDesTraitements": {"etat": {"code": "RT", "libelle": "Retir\u00e9"}, "sousEtat": {"code": "RT", "libelle": "Retir\u00e9 apr\u00e8s publication"}}, "dateSort": {"@xmlns:xsi": "http://www.w3.org/2001/XMLSchema-instance", "@xsi:nil": "true"}, "sort": {"@xmlns:xsi": "http://www.w3.org/2001/XMLSchema-instance", "@xsi:nil": "true"}}, "representations": {"representation": {"nom": "PDF", "typeMime": {"type": "application", "subType": "PDF"}, "statutRepresentation": {"verbatim": "true", "canonique": "true", "officielle": "true", "transcription": "false", "enregistrement": "false"}, "repSource": {"@xmlns:xsi": "http://www.w3.org/2001/XMLSchema-instance", "@xsi:nil": "true"}, "offset": {"@xmlns:xsi": "http://www.w3.org/2001/XMLSchema-instance", "@xsi:nil": "true"}, "contenu": {"documentURI": "/base/AMANR5L17PO838901BTC1281P0D1N000794?format=pdf"}, "dateDispoRepresentation": {"@xmlns:xsi": "http://www.w3.org/2001/XMLSchema-instance", "@xsi:nil": "true"}}}, "seanceDiscussionRef": {"@xmlns:xsi": "http://www.w3.org/2001/XMLSchema-instance", "@xsi:nil": "true"}, "article99": "false", "loiReference": {"@xmlns:xsi": "http://www.w3.org/2001/XMLSchema-instance", "@xsi:nil": "true"}, "discussionCommune": {"@xmlns:xsi": "http://www.w3.org/2001/XMLSchema-instance", "@xsi:nil": "true"}, "discussionIdentique": {"@xmlns:xsi": "http://www.w3.org/2001/XMLSchema-instance", "@xsi:nil": "true"}, "accordGouvernementDepotHorsDelai": "Sans objet"}}