{"amendement": {"@xmlns": "http://schemas.assemblee-nationale.fr/referentiel", "uid": "AMANR5L17PO838901BTC1364P0D1N001432", "chronotag": "1757948575110", "legislature": "17", "identification": {"numeroLong": "1432", "numeroOrdreDepot": "1432", "prefixeOrganeExamen": "AN", "numeroRect": "0"}, "examenRef": "EXANR5L17PO838901BTC1364P0D1", "texteLegislatifRef": "PIONANR5L17BTC1364", "triAmendement": "blaaaaaaaaaaaaaaaaaaaaaaaaaaaaaaaaaaaaaaaaaaaaaaaafozzs", "cardinaliteAmdtMultiples": "1", "amendementParentRef": {"@xmlns:xsi": "http://www.w3.org/2001/XMLSchema-instance", "@xsi:nil": "true"}, "signataires": {"auteur": {"typeAuteur": "D\u00e9put\u00e9", "gouvernementRef": {"@xmlns:xsi": "http://www.w3.org/2001/XMLSchema-instance", "@xsi:nil": "true"}, "acteurRef": "PA840809", "groupePolitiqueRef": "PO847173", "auteurRapporteurOrganeRef": {"@xmlns:xsi": "http://www.w3.org/2001/XMLSchema-instance", "@xsi:nil": "true"}}, "cosignataires": {"@xmlns:xsi": "http://www.w3.org/2001/XMLSchema-instance", "@xsi:nil": "true"}, "suffixe": {"@xmlns:xsi": "http://www.w3.org/2001/XMLSchema-instance", "@xsi:nil": "true"}, "libelle": "M.&#160;Verny"}, "pointeurFragmentTexte": {"partieAmendableRef": {"@xmlns:xsi": "http://www.w3.org/2001/XMLSchema-instance", "@xsi:nil": "true"}, "division": {"titre": "Article 5", "articleDesignationCourte": "ART. 5", "articleDesignation": "ARTICLE 5", "type": "ARTICLE", "avant_A_Apres": "A", "divisionRattachee": {"@xmlns:xsi": "http://www.w3.org/2001/XMLSchema-instance", "@xsi:nil": "true"}, "articleAdditionnel": "false", "chapitreAdditionnel": "false", "urlDivisionTexteVise": "/17/textes/1364.asp#D_Article_5"}, "amendementStandard": {"alinea": {"avant_A_Apres": {"@xmlns:xsi": "http://www.w3.org/2001/XMLSchema-instance", "@xsi:nil": "true"}, "numero": "11", "alineaDesignation": "Alin\u00e9a 11"}}}, "corps": {"cartoucheInformatif": {"@xmlns:xsi": "http://www.w3.org/2001/XMLSchema-instance", "@xsi:nil": "true"}, "contenuAuteur": {"dispositif": "<p style=\"text-align: justify;\">&#x00C0;&nbsp;la fin de l&#x2019;alin&#x00E9;a&nbsp;11, substituer aux mots&nbsp;:&nbsp;</p><p style=\"text-align: justify;\">&#x00AB;&nbsp;ou un psychiatre&nbsp;&#x00BB;,</p><p style=\"text-align: justify;\">les mots&nbsp;:&nbsp;</p><p style=\"text-align: justify;\">&#x00AB;&nbsp;clinicien et un psychiatre inscrits &#x00E0; un registre national valid&#x00E9; par la Haute Autorit&#x00E9; de Sant&#x00E9;.&nbsp;&#x00BB;</p>", "avantAppel": {"@xmlns:xsi": "http://www.w3.org/2001/XMLSchema-instance", "@xsi:nil": "true"}, "exposeSommaire": "<p>Le pr&#x00E9;sent amendement vise &#x00E0; renforcer les garanties professionnelles et institutionnelles entourant l&#x2019;&#x00E9;valuation psychique de la personne demandant l&#x2019;aide &#x00E0; mourir.</p><p>Ce doublement des intervenants sp&#x00E9;cialis&#x00E9;s r&#x00E9;pond &#x00E0; l&#x2019;exigence d&#x2019;une expertise plurielle et crois&#x00E9;e, indispensable pour appr&#x00E9;cier avec rigueur la stabilit&#x00E9; psychique, la capacit&#x00E9; de discernement, et l&#x2019;absence de pathologie mentale alt&#x00E9;rant le consentement. En exigeant l&#x2019;intervention conjointe d&#x2019;un psychologue clinicien, form&#x00E9; &#x00E0; l&#x2019;&#x00E9;valuation clinique et au suivi th&#x00E9;rapeutique, et d&#x2019;un psychiatre, comp&#x00E9;tent en mati&#x00E8;re diagnostique et pharmacologique, l&#x2019;amendement vise &#x00E0; garantir une &#x00E9;valuation compl&#x00E8;te et convergente.</p><p>Par ailleurs, l&#x2019;inscription sur un registre national valid&#x00E9; par la HAS permet de s&#x2019;assurer du haut niveau de comp&#x00E9;tence des professionnels intervenants, de leur formation sp&#x00E9;cifique aux enjeux &#x00E9;thiques de la fin de vie, ainsi que de leur ind&#x00E9;pendance vis-&#x00E0;-vis de l&#x2019;&#x00E9;quipe soignante. Il s&#x2019;agit d&#x2019;une condition essentielle &#x00E0; la qualit&#x00E9;, &#x00E0; la l&#x00E9;gitimit&#x00E9; et &#x00E0; la s&#x00E9;curit&#x00E9; du processus.</p>", "annexeExposeSommaire": {"@xmlns:xsi": "http://www.w3.org/2001/XMLSchema-instance", "@xsi:nil": "true"}}}, "cycleDeVie": {"dateDepot": "2025-05-09", "datePublication": "2025-05-20", "soumisArticle40": "true", "etatDesTraitements": {"etat": {"code": "RT", "libelle": "Retir\u00e9"}, "sousEtat": {"code": "RT", "libelle": "Retir\u00e9 apr\u00e8s publication"}}, "dateSort": {"@xmlns:xsi": "http://www.w3.org/2001/XMLSchema-instance", "@xsi:nil": "true"}, "sort": {"@xmlns:xsi": "http://www.w3.org/2001/XMLSchema-instance", "@xsi:nil": "true"}}, "representations": {"representation": {"nom": "PDF", "typeMime": {"type": "application", "subType": "PDF"}, "statutRepresentation": {"verbatim": "true", "canonique": "true", "officielle": "true", "transcription": "false", "enregistrement": "false"}, "repSource": {"@xmlns:xsi": "http://www.w3.org/2001/XMLSchema-instance", "@xsi:nil": "true"}, "offset": {"@xmlns:xsi": "http://www.w3.org/2001/XMLSchema-instance", "@xsi:nil": "true"}, "contenu": {"documentURI": "/base/AMANR5L17PO838901BTC1364P0D1N001432?format=pdf"}, "dateDispoRepresentation": {"@xmlns:xsi": "http://www.w3.org/2001/XMLSchema-instance", "@xsi:nil": "true"}}}, "seanceDiscussionRef": {"@xmlns:xsi": "http://www.w3.org/2001/XMLSchema-instance", "@xsi:nil": "true"}, "article99": "false", "loiReference": {"codeLoi": "1", "divisionCodeLoi": {"@xmlns:xsi": "http://www.w3.org/2001/XMLSchema-instance", "@xsi:nil": "true"}}, "discussionCommune": {"@xmlns:xsi": "http://www.w3.org/2001/XMLSchema-instance", "@xsi:nil": "true"}, "discussionIdentique": {"@xmlns:xsi": "http://www.w3.org/2001/XMLSchema-instance", "@xsi:nil": "true"}, "accordGouvernementDepotHorsDelai": "Sans objet"}}