{"amendement": {"@xmlns": "http://schemas.assemblee-nationale.fr/referentiel", "uid": "AMANR5L17PO838901BTC1364P0D1N002619", "chronotag": "1757948441204", "legislature": "17", "identification": {"numeroLong": "2619", "numeroOrdreDepot": "2619", "prefixeOrganeExamen": "AN", "numeroRect": "0"}, "examenRef": "EXANR5L17PO838901BTC1364P0D1", "texteLegislatifRef": "PIONANR5L17BTC1364", "triAmendement": "beaaaaaaaaaaaaaaaaaaaaaaaaaaaaaaaaaaaaaaaaaaaaaaaajzzzzzgvzzzef", "cardinaliteAmdtMultiples": "1", "amendementParentRef": {"@xmlns:xsi": "http://www.w3.org/2001/XMLSchema-instance", "@xsi:nil": "true"}, "signataires": {"auteur": {"typeAuteur": "D\u00e9put\u00e9", "gouvernementRef": {"@xmlns:xsi": "http://www.w3.org/2001/XMLSchema-instance", "@xsi:nil": "true"}, "acteurRef": "PA346782", "groupePolitiqueRef": "PO845425", "auteurRapporteurOrganeRef": {"@xmlns:xsi": "http://www.w3.org/2001/XMLSchema-instance", "@xsi:nil": "true"}}, "cosignataires": {"acteurRef": ["PA642847", "PA774954", "PA840979", "PA330008", "PA793508", "PA1327", "PA719968", "PA608416", "PA606098", "PA842141", "PA720386", "PA793094", "PA794058"]}, "suffixe": {"@xmlns:xsi": "http://www.w3.org/2001/XMLSchema-instance", "@xsi:nil": "true"}, "libelle": "M.&#160;Juvin,  M.&#160;Bazin, Mme&#160;Blin, M.&#160;Le&#160;Fur, M.&#160;Breton, M.&#160;Brigand, M.&#160;Forissier, Mme&#160;Sylvie&#160;Bonnet, M.&#160;Hetzel, M.&#160;Marleix, Mme&#160;de&#160;Maistre, M.&#160;Di&#160;Filippo, M.&#160;Ray et Mme&#160;Gruet"}, "pointeurFragmentTexte": {"partieAmendableRef": {"@xmlns:xsi": "http://www.w3.org/2001/XMLSchema-instance", "@xsi:nil": "true"}, "division": {"titre": "Article 4", "articleDesignationCourte": "ART. 4", "articleDesignation": "ARTICLE 4", "type": "ARTICLE", "avant_A_Apres": "A", "divisionRattachee": {"@xmlns:xsi": "http://www.w3.org/2001/XMLSchema-instance", "@xsi:nil": "true"}, "articleAdditionnel": "false", "chapitreAdditionnel": "false", "urlDivisionTexteVise": "/17/textes/1364.asp#D_Article_4"}, "amendementStandard": {"alinea": {"avant_A_Apres": "Apres", "numero": "9", "alineaDesignation": "Apr\u00e8s l'alin\u00e9a 9"}}}, "corps": {"cartoucheInformatif": {"@xmlns:xsi": "http://www.w3.org/2001/XMLSchema-instance", "@xsi:nil": "true"}, "contenuAuteur": {"dispositif": "<p style=\"text-align: justify;\">Compl&#x00E9;ter cet article par l&#x2019;alin&#x00E9;a suivant&nbsp;:</p><p style=\"text-align: justify;\">&#x00AB;&nbsp;Lorsque la personne fait l&#x2019;objet d&#x2019;une mesure de protection juridique avec assistance ou repr&#x00E9;sentation, le juge des contentieux de la protection confirme le caract&#x00E8;re libre et &#x00E9;clair&#x00E9; du consentement.&nbsp;&#x00BB;</p>", "avantAppel": {"@xmlns:xsi": "http://www.w3.org/2001/XMLSchema-instance", "@xsi:nil": "true"}, "exposeSommaire": "<p style=\"text-align: justify;\">Cet amendement vise &#x00E0; mieux encadrer le suicide assist&#x00E9; et l&#x2019;euthanasie en faisant du juge des contentieux de la protection le gardien de l&#x2019;ensemble des crit&#x00E8;res &#x00E9;nonc&#x00E9;s &#x00E0; cet article.</p>", "annexeExposeSommaire": {"@xmlns:xsi": "http://www.w3.org/2001/XMLSchema-instance", "@xsi:nil": "true"}}}, "cycleDeVie": {"dateDepot": "2025-05-09", "datePublication": "2025-05-19", "soumisArticle40": "false", "etatDesTraitements": {"etat": {"code": "DI", "libelle": "Discut\u00e9"}, "sousEtat": {"code": "DI", "libelle": "Rejet\u00e9"}}, "dateSort": "2025-05-19T23:23:40+02:00", "sort": "Rejet\u00e9"}, "representations": {"representation": {"nom": "PDF", "typeMime": {"type": "application", "subType": "PDF"}, "statutRepresentation": {"verbatim": "true", "canonique": "true", "officielle": "true", "transcription": "false", "enregistrement": "false"}, "repSource": {"@xmlns:xsi": "http://www.w3.org/2001/XMLSchema-instance", "@xsi:nil": "true"}, "offset": {"@xmlns:xsi": "http://www.w3.org/2001/XMLSchema-instance", "@xsi:nil": "true"}, "contenu": {"documentURI": "/base/AMANR5L17PO838901BTC1364P0D1N002619?format=pdf"}, "dateDispoRepresentation": {"@xmlns:xsi": "http://www.w3.org/2001/XMLSchema-instance", "@xsi:nil": "true"}}}, "seanceDiscussionRef": "RUANR5L17S2025IDS29390", "article99": "false", "loiReference": {"@xmlns:xsi": "http://www.w3.org/2001/XMLSchema-instance", "@xsi:nil": "true"}, "discussionCommune": {"idDiscussion": "31044", "typePosition": "Dernier"}, "discussionIdentique": {"@xmlns:xsi": "http://www.w3.org/2001/XMLSchema-instance", "@xsi:nil": "true"}, "accordGouvernementDepotHorsDelai": "Sans objet"}}